loan_amount_model_package/VERSION
loan_amount_model_package/__init__.py
loan_amount_model_package/config/__init__.py
loan_amount_model_package/config/core.py
loan_amount_model_package/config.yml
loan_amount_model_package/datasets/__init__.py
loan_amount_model_package/datasets/test.csv
loan_amount_model_package/datasets/train.csv
loan_amount_model_package/pipeline.py
loan_amount_model_package/predict.py
loan_amount_model_package/processing/__init__.py
loan_amount_model_package/processing/data_manager.py
loan_amount_model_package/processing/preprocessor.py
loan_amount_model_package/processing/validation.py
loan_amount_model_package/train_pipeline.py
loan_amount_model_package/trained_models/__init__.py
loan_amount_model_package/trained_models/loan_pred_regression_model_output_v0.0.7.pkl
loan_amount_model_package-0.0.7.dist-info/METADATA
loan_amount_model_package-0.0.7.dist-info/WHEEL
loan_amount_model_package-0.0.7.dist-info/RECORD
