Metadata-Version: 2.1
Name: loan_amount_model_package
Version: 0.0.7
Summary: A model package to estimate loan amount suitable for a customer
Author: chibuikeeugene
Author-email: chibuikeeugene@gmail.com
Requires-Python: >=3.9,<4.0
Classifier: Programming Language :: Python :: 3
Classifier: Programming Language :: Python :: 3.9
Classifier: Programming Language :: Python :: 3.10
Classifier: Programming Language :: Python :: 3.11
Classifier: Programming Language :: Python :: 3.12
